MANIFEST.in
README.md
setup.cfg
setup.py
coinwise/__init__.py
coinwise/coinwise.py
coinwise/coinwise_confs.py
coinwise/exceptions.py
coinwise_sdk.egg-info/PKG-INFO
coinwise_sdk.egg-info/SOURCES.txt
coinwise_sdk.egg-info/dependency_links.txt
coinwise_sdk.egg-info/not-zip-safe
coinwise_sdk.egg-info/requires.txt
coinwise_sdk.egg-info/top_level.txt
test/__init__.py
test/staging_test.py
test/staging_test_confs.py