Metadata-Version: 2.1
Name: coinwise-sdk
Version: 0.1
Summary: CoinWise integration
Home-page: https://github.com/GuilhermeGPG/coinwise-sdk
Author: Guilherme Gomides
Author-email: guilhermepgomides@gmail.com
License: MIT
Keywords: Coinwise integration
Platform: UNKNOWN
Classifier: Development Status :: 3 - Alpha
Classifier: Intended Audience :: Developers
Classifier: Topic :: Software Development :: Build Tools
Classifier: License :: OSI Approved :: MIT License
Classifier: Programming Language :: Python :: 3
Classifier: Programming Language :: Python :: 3.4
Classifier: Programming Language :: Python :: 3.5
Classifier: Programming Language :: Python :: 3.6
